[
    {
        "Name": "Faktura",
        "Code": "invoice_list",
        "Type": "Table",
        "IsTopLevelTicker": true,
        "Group": "Salg",
        "Model": "CustomerInvoice",
        "Expand": "Customer.Info",
        "Columns": [
            {
                "Header": "Fakturanr",
                "Field": "InvoiceNumber",
                "Width": "100px",
                "Type": "text"
            },
            {
                "Header": "Kundenr",
                "Field": "Customer.CustomerNumber",
                "Type": "text"
            },
            {
                "Header": "Kundenavn",
                "Field": "Customer.Info.Name",
                "Width": "250px"
            },
            {
                "Header": "Fakturadato",
                "Field": "InvoiceDate"
            },
            {
                "Header": "Forfallsdato",
                "Field": "PaymentDueDate",
                "Format": "DatePassed"
            },
            {
                "Header": "Sum inkl mva",
                "Field": "TaxInclusiveAmount",
                "Format": "NumberPositiveNegative",
                "Width": "150px"
            },
            {
                "Header": "Status",
                "Field": "StatusCode"
            }
        ],
        "ParentFilter": {
            "Field": "CustomerID",
            "Operator": "eq",
            "Value": "ID"
        },
        "Actions": [
            {
                "Name": "Ny faktura",
                "Code": "new_invoice",
                "ExecuteWithoutSelection": true,
                "Type": "new"
            },
            {
                "Name": "Åpne faktura",
                "Code": "open_invoice",
                "Type": "details",
                "DisplayInContextMenu": true,
                "DisplayInActionBar": true
            },
            {
                "Name": "Eksporter",
                "Code": "export_invoices",
                "Type": "export",
                "ExecuteWithMultipleSelections": true,
                "ExecuteWithoutSelection": true
            },
            {
                "Name": "Kopier",
                "Code": "copy_invoice",
                "ConfirmBeforeExecuteMessage": "Er du sikker på at du vil kopiere valgt faktura?",
                "Type": "action",
                "Action": "copy",
                "DisplayInContextMenu": true,
                "DisplayInActionBar": false
            },
            {
                "Name": "Fakturer",
                "Code": "invoice_invoice",
                "Type": "transition",
                "Transition": "invoice",
                "DisplayInContextMenu": true,
                "DisplayInActionBar": false
            }
        ],
        "SubTickersCodes": ["invoice_details", "invoice_items"],
        "Filters": [
            {
                "Name": "Alle",
                "Code": "all_invoices",
                "Filter": ""
            },
            {
                "Name": "Mine under arbeid",
                "Code": "my_draft_invoices",
                "UseAllCriterias": true,
                "FilterGroups": [{
                    "UseAllCriterias": true,
                    "FieldFilters": [
                    {
                        "Field": "StatusCode",
                        "Operator": "eq",
                        "Value": "42001"
                    },
                    {
                        "Field": "CreatedBy",
                        "Operator": "eq",
                        "Value": ":currentuserid"
                    }]
                }]
            },
            {
                "Name": "Forfalte",
                "Code": "due_invoices",
                "Filter": "PaymentDueDate lt getdate()"
            },
            {
                "Name": "Mine større enn 2000",
                "Code": "my_invoices",
                "UseAllCriterias": true,
                "FilterGroups": [{
                    "FieldFilters": [
                    {
                        "Field": "TaxInclusiveAmount",
                        "Operator": "gt",
                        "Value": "2000"
                    },
                    {
                        "Field": "CreatedBy",
                        "Operator": "eq",
                        "Value": ":currentuserid"
                    }]
                }]
            }
        ]
    },
    {
        "Name": "Tilbud",
        "Code": "quote_list",
        "Type": "Table",
        "IsTopLevelTicker": true,
        "Group": "Salg",
        "Model": "CustomerQuote",
        "Expand": "Customer.Info",
        "Columns": [
            {
                "Field": "QuoteNumber",
                "Width": "100px",
                "Type": "text"
            },
            {
                "Field": "Customer.CustomerNumber",
                "Type": "text"
            },
            {
                "Field": "Customer.Info.Name",
                "Width": "250px"
            },
            {
                "Field": "QuoteDate"
            },
            {
                "Field": "ValidUntilDate",
                "Format": "DatePassed"
            },
            {
                "Field": "TaxInclusiveAmount",
                "Format": "NumberPositiveNegative",
                "Width": "150px"
            },
            {
                "Header": "Status",
                "Field": "StatusCode"
            }
        ],
        "ParentFilter": {
            "Field": "CustomerID",
            "Operator": "eq",
            "Value": "ID"
        },
        "Actions": [
            {
                "Name": "Nytt tilbud",
                "Code": "new_quote",
                "ExecuteWithoutSelection": true,
                "Type": "new"
            },
            {
                "Name": "Åpne tilbud",
                "Code": "open_quote",
                "Type": "details",
                "DisplayInContextMenu": true,
                "DisplayInActionBar": true
            },
            {
                "Name": "Eksporter",
                "Code": "export_quotes",
                "Type": "export",
                "ExecuteWithMultipleSelections": true,
                "ExecuteWithoutSelection": true
            },
            {
                "Name": "Overfør til ordre",
                "Code": "quote_transfer_order",
                "Type": "transition",
                "Transition": "toOrder",
                "DisplayInContextMenu": true,
                "DisplayInActionBar": false
            },
            {
                "Name": "Overfør til faktura",
                "Code": "quote_transfer_invoice",
                "Type": "transition",
                "Transition": "toInvoice",
                "DisplayInContextMenu": true,
                "DisplayInActionBar": false
            },
            {
                "Name": "Avslutt",
                "Code": "quote_transfer_complete",
                "Type": "transition",
                "Transition": "complete",
                "DisplayInContextMenu": true,
                "DisplayInActionBar": false
            }
        ],
        "SubTickersCodes": [],
        "Filters": [
            {
                "Name": "Alle",
                "Code": "all_quotes",
                "Filter": ""
            },
            {
                "Name": "Mine under arbeid",
                "Code": "my_draft_quotes",
                "UseAllCriterias": true,
                "FilterGroups": [{
                    "UseAllCriterias": true,
                    "FieldFilters": [
                    {
                        "Field": "StatusCode",
                        "Operator": "eq",
                        "Value": "40001"
                    },
                    {
                        "Field": "CreatedBy",
                        "Operator": "eq",
                        "Value": ":currentuserid"
                    }]
                }]
            }
        ]
    },
    {
        "Name": "Kunde",
        "Code": "customer_list",
        "Type": "Table",
        "IsTopLevelTicker": true,
        "Group": "Salg",
        "Model": "Customer",
        "Expand": "Info,Info.DefaultEmail,Info.DefaultPhone,Info.InvoiceAddress",
        "Columns": [
            {
                "Header": "Kundenr",
                "Field": "Customer.CustomerNumber",
                "Type": "text",
                "Width": "120px"
            },
            {
                "Header": "Navn",
                "Field": "Customer.Info.Name",
                "Width": "250px"
            },
            {
                "Header": "Telefon",
                "Field": "Info.DefaultPhone.Number"
            },
            {
                "Header": "Epost",
                "Field": "Info.DefaultEmail.EmailAddress"
            },
            {
                "Header": "Adresse",
                "Field": "Info.InvoiceAddress.AddressLine1"
            },
            {
                "Header": "Postnr",
                "Field": "Info.InvoiceAddress.PostalCode"
            },
            {
                "Header": "Sted",
                "Field": "Info.InvoiceAddress.City"
            }
        ],
        "Actions": [
            {
                "Name": "Ny kunde",
                "Code": "new_customer",
                "ExecuteWithoutSelection": true,
                "Type": "new"
            },
            {
                "Name": "Vis kunde",
                "Code": "open_customer",
                "Type": "details",
                "DisplayInContextMenu": true,
                "DisplayInActionBar": true
            },
            {
                "Name": "Eksporter",
                "Code": "export_customers",
                "Type": "export",
                "ExecuteWithMultipleSelections": true,
                "ExecuteWithoutSelection": true
            }
        ],
        "SubTickersCodes": ["invoice_list", "order_list", "quote_list"],
        "Filters": [
            {
                "Name": "Alle",
                "Code": "all_customers",
                "Filter": ""
            },
            {
                "Name": "Mine kunder",
                "Code": "my_customers",
                "UseAllCriterias": true,
                "FilterGroups": [{
                    "UseAllCriterias": true,
                    "FieldFilters": [
                    {
                        "Field": "CreatedBy",
                        "Operator": "eq",
                        "Value": ":currentuserid"
                    }]
                }]
            }
        ]
    },
    {
        "Name": "Ordre",
        "Type": "Table",
        "Code": "order_list",
        "IsTopLevelTicker": true,
        "Group": "Salg",
        "Model": "CustomerOrder",
        "Expand": "Customer.Info",
        "Columns": [
            {
                "Field": "OrderNumber",
                "Width": "100px",
                "Type": "text"
            },
            {
                "Field": "Customer.CustomerNumber",
                "Type": "text"
            },
            {
                "Field": "Customer.Info.Name",
                "Width": "250px"
            },
            {
                "Field": "OrderDate"
            },
            {
                "Field": "TaxInclusiveAmount",
                "Format": "NumberPositiveNegative",
                "Width": "150px"
            },
            {
                "Header": "Status",
                "Field": "StatusCode"
            }
        ],
        "ParentFilter": {
            "Field": "CustomerID",
            "Operator": "eq",
            "Value": "ID"
        },
        "Actions": [
            {
                "Name": "Åpne ordre",
                "Code": "open_order",
                "Type": "details",
                "DisplayInContextMenu": true,
                "DisplayInActionBar": true
            }
        ]
    },
    {
        "Name": "Eksterne data - test",
        "Type": "Table",
        "Code": "external_data_test_list",
        "ApiUrl": "https://jsonplaceholder.typicode.com/posts",
        "ListObject": "",
        "IsTopLevelTicker": false,
        "DisableFiltering": true,
        "Group": "Test",
        "Columns": [
            {
                "Header": "Tittel",
                "Field": "title",
                "Width": "250px"
            },
            {
                "Header": "Tekst",
                "Field": "body"
            }
        ]
    },
    {
        "Name": "Eksterne data - forsiden VG.no",
        "Type": "Table",
        "Code": "external_data_forsiden_vg",
        "ApiUrl": "https://api.rss2json.com/v1/api.json?rss_url=http%3A%2F%2Fwww.vg.no%2Frss%2Ffeed%2Fforsiden",
        "ListObject": "items",
        "IsTopLevelTicker": false,
        "DisableFiltering": true,
        "Group": "Test",
        "Columns": [
            {
                "Header": "Tittel",
                "Field": "title"
            },
            {
                "Header": "Link",
                "Field": "link",
                "Type": "external-link"
            }
        ]
    },
    {
        "Name": "Fakturalinjer",
        "Type": "Table",
        "Code": "invoice_items",
        "IsTopLevelTicker": false,
        "Group": "Salg",
        "Model": "CustomerInvoiceItem",
        "Expand": "Product",
        "SubTickers": [],
        "ParentFilter": {
            "Field": "CustomerInvoiceID",
            "Operator": "eq",
            "Value": "ID"
        },
        "Filters": [
            {
                "Name": "Alle linjer",
                "Code": "all_invoice_items",
                "Filter": ""
            },
            {
                "Name": "Mest lønnsomme",
                "Code": "most_valuable_items",
                "Filter": ""
            }
        ],
        "Columns": [
            {
                "Header": "Produkt",
                "Field": "Product.Name",
                "Width": "250px"
            },
            {
                "Header": "Antall",
                "Field": "NumberOfItems",
                "Format": "number"
            },
            {
                "Header": "Sum inkl mva",
                "Field": "SumTotalIncVat",
                "Format": "NumberPositiveNegative",
                "Width": "150px",
                "Type": "money"
            }
        ]
    },
    {
        "Name": "Fakturadetaljer",
        "Type": "Details",
        "Code": "invoice_details",
        "IsTopLevelTicker": false,
        "Group": "Salg",
        "Model": "CustomerInvoice",
        "Expand": "Customer.Info",
        "SubTickers": [],
        "Filters": [],
        "ParentFilter": {
            "Field": "ID",
            "Operator": "eq",
            "Value": "ID"
        },
        "Columns": [
            {
                "Header": "Fakturanr",
                "Field": "InvoiceNumber"
            },
            {
                "Header": "Kundenavn",
                "Field": "Customer.Info.Name"
            },
            {
                "Header": "Forfallsdato",
                "Field": "PaymentDueDate"
            },
            {
                "Header": "Adresse",
                "Field": "InvoiceAddressLine1",
                "Size": "medium",
                "SubFields": [
                    {
                        "Field": "InvoicePostalCode"
                    },
                    {
                        "Field": "InvoiceCity"
                    }
                ]
            },
            {
                "Header": "Vår referanse",
                "Field": "OurReference"
            },
            {
                "Header": "Sum inkl mva",
                "Field": "TaxInclusiveAmount"
            }
        ]
    }

]
